setup.py
bgd_distributions/Binomialdistribution.py
bgd_distributions/Gaussiandistribution.py
bgd_distributions/Generaldistribution.py
bgd_distributions/__init__.py
bgd_distributions.egg-info/PKG-INFO
bgd_distributions.egg-info/SOURCES.txt
bgd_distributions.egg-info/dependency_links.txt
bgd_distributions.egg-info/not-zip-safe
bgd_distributions.egg-info/top_level.txt