Metadata-Version: 1.0
Name: bgd-distributions
Version: 0.1
Summary: Gaussian and Binomial distributions
Home-page: UNKNOWN
Author: Tamiris Martins
Author-email: tamiriscrepalde@gmail.com
License: UNKNOWN
Platform: UNKNOWN
